avtomatika_worker/__init__.py
avtomatika_worker/config.py
avtomatika_worker/types.py
avtomatika_worker/worker.py
tg_runner_worker_sdk-1.0.0.dist-info/licenses/LICENSE
tg_runner_worker_sdk-1.0.0.dist-info/METADATA
tg_runner_worker_sdk-1.0.0.dist-info/WHEEL
tg_runner_worker_sdk-1.0.0.dist-info/top_level.txt
tg_runner_worker_sdk-1.0.0.dist-info/RECORD
