Metadata-Version: 2.4
Name: tg-runner-worker-sdk
Version: 1.0.0
Summary: Worker SDK for TG Runner orchestrator - build distributed workers easily
Author: TimaxLacs
License: MIT
Project-URL: Homepage, https://github.com/TimaxLacs/tg-runner-worker-sdk
Project-URL: Repository, https://github.com/TimaxLacs/tg-runner-worker-sdk
Keywords: worker,orchestrator,distributed,async,telegram,bot
Classifier: Development Status :: 4 - Beta
Classifier: Intended Audience :: Developers
Classifier: Programming Language :: Python :: 3
Classifier: Programming Language :: Python :: 3.10
Classifier: Programming Language :: Python :: 3.11
Classifier: Programming Language :: Python :: 3.12
Classifier: Framework :: AsyncIO
Requires-Python: >=3.10
License-File: LICENSE
Requires-Dist: aiohttp>=3.9.0
Requires-Dist: python-json-logger>=2.0.0
Dynamic: license-file
